contextforce_python/__init__.py
contextforce_python/main.py
contextforce_python/multi-asyncio.py
contextforce_python/single-asyncio.py
contextforce_python-0.3.0.dist-info/LICENSE
contextforce_python-0.3.0.dist-info/METADATA
contextforce_python-0.3.0.dist-info/WHEEL
contextforce_python-0.3.0.dist-info/RECORD
