Metadata-Version: 2.1
Name: contextforce-python
Version: 0.3.0
Summary: 
Author: developer
Author-email: contextforce01@gmail.com
Requires-Python: >=3.8,<4.0
Classifier: Programming Language :: Python :: 3
Classifier: Programming Language :: Python :: 3.8
Classifier: Programming Language :: Python :: 3.9
Classifier: Programming Language :: Python :: 3.10
Classifier: Programming Language :: Python :: 3.11
Classifier: Programming Language :: Python :: 3.12
Requires-Dist: httpx[http2] (>=0.27.0,<0.28.0)
Requires-Dist: pytest (>=8.3.2,<9.0.0)
Requires-Dist: setuptools (>=72.1.0,<73.0.0)
Requires-Dist: twine (>=5.1.1,<6.0.0)
Requires-Dist: wheel (>=0.44.0,<0.45.0)
